better_orderedmultidict/__init__.py
better_orderedmultidict/_multidict.py
better_orderedmultidict/_orderedmultidict.py
better_orderedmultidict/py.typed
better_orderedmultidict-0.2.2.dist-info/licenses/LICENSE
better_orderedmultidict-0.2.2.dist-info/METADATA
better_orderedmultidict-0.2.2.dist-info/WHEEL
better_orderedmultidict-0.2.2.dist-info/top_level.txt
better_orderedmultidict-0.2.2.dist-info/RECORD
