Metadata-Version: 2.4
Name: better_orderedmultidict
Version: 0.2.2
Summary: Ordered Multivalue Dictionary
Author-email: Joachim Coenen <joachimcoenen@icloud.com>
Project-URL: Homepage, https://github.com/JoachimCoenen/Better-OrderedMultiDict
Project-URL: Issues, https://github.com/JoachimCoenen/Better-OrderedMultiDict/issues
Classifier: Programming Language :: Python :: 3.12
Classifier: License :: OSI Approved :: MIT License
Classifier: Operating System :: OS Independent
Requires-Python: >=3.12
License-File: LICENSE
Dynamic: license-file
